matflow_mtex/__init__.py
matflow_mtex/_version.py
matflow_mtex/main.py
matflow_mtex/scripting.py
matflow_mtex/utils.py
matflow_mtex/snippets/ensure_1D_matrix.m
matflow_mtex/snippets/ensure_2D_cell_array.m
matflow_mtex/snippets/ensure_double.m
matflow_mtex/snippets/export_ODF.m
matflow_mtex/snippets/export_orientations.m
matflow_mtex/snippets/export_orientations_JSON.m
matflow_mtex/snippets/get_EBSD_orientations_from_CRC_file.m
matflow_mtex/snippets/get_EBSD_orientations_from_CTF_file.m
matflow_mtex/snippets/get_ODF_from_CRC_file.m
matflow_mtex/snippets/get_ODF_from_CTF_file.m
matflow_mtex/snippets/get_ODF_from_EBSD_orientations.m
matflow_mtex/snippets/get_fibre_ODF.m
matflow_mtex/snippets/get_model_ODF.m
matflow_mtex/snippets/get_random_ODF.m
matflow_mtex/snippets/get_unimodal_ODF.m
matflow_mtex/snippets/load_ODF.m
matflow_mtex/snippets/load_ODF_mat.m
matflow_mtex/snippets/plot_pole_figure.m
matflow_mtex/snippets/randomly_sample_EBSD_orientations.m
matflow_mtex/snippets/sample_ODF_orientations.m
matflow_mtex-0.1.11.dist-info/LICENSE
matflow_mtex-0.1.11.dist-info/METADATA
matflow_mtex-0.1.11.dist-info/WHEEL
matflow_mtex-0.1.11.dist-info/entry_points.txt
matflow_mtex-0.1.11.dist-info/top_level.txt
matflow_mtex-0.1.11.dist-info/RECORD
